{"headline": "Cannes Curveball: Jacob Elordi's Festival Dreams Hobbled by Injury", "lede": "Actor Jacob Elordi faces unexpected setback as a broken foot threatens his high-profile jury appearance at the Cannes Film Festival.", "body": "Hollywood's rising star Jacob Elordi will not be making his anticipated Cannes Film Festival jury debut as planned, after sustaining a significant foot injury that derails his festival commitments.\n\nThe 'Euphoria' breakout and recent 'Frankenstein' lead was poised to bring youthful energy to the prestigious competition jury. Instead, Elordi will now be sidelined, watching the glamorous proceedings from afar while recovering from his unexpected medical complication.\n\nElordi's packed professional calendar \u2014 which recently included critically discussed turns in 'Wuthering Heights' and the latest 'Euphoria' season \u2014 suddenly encounters an unscripted pause. The injury arrives at a critical moment for the actor, whose international profile continues ascending rapidly through diverse dramatic roles.\n\nFilm festival circuits are notoriously unpredictable, and Elordi's absence represents a surprising twist in what was expected to be a breakthrough moment for the young actor. Festival organizers will likely need to quickly recalibrate their jury composition in his absence.\n\nWhile specific medical details remain limited, the foot injury appears significant enough to completely preclude Elordi's participation in the upcoming Cannes proceedings.", "key_facts": ["Elordi was set to serve on Cannes Film Festival jury", "Broken foot prevents festival appearance", "Actor recently starred in 'Euphoria' and 'Frankenstein'", "Injury interrupts rising career momentum"], "category": "cancellations", "confidence_score": 8, "sources_used": ["hollywoodreporter.com"], "show_title": "Euphoria", "show_ids": [], "story_hash": "039fe3416bad5ecb", "published_at": "2026-05-06T01:10:18.393821+00:00", "source_url": "https://www.hollywoodreporter.com/movies/movie-news/jacob-elordi-foot-injury-cannes-film-festival-jury-1236587375/", "source_domain": "hollywoodreporter.com", "image_url": "https://image.tmdb.org/t/p/w1280/mez2Z3WqlPKNXpi7mWoiiE5guE9.jpg", "image_source": "tmdb", "passes": true, "max_similarity": 0.2623}