{"headline": "Demi Moore, Woody Harrelson Weaponize Streaming to Spotlight Climate Action", "lede": "Prime Video's provocative new documentary 'Groundswell' promises a cinematic rallying cry for environmental transformation, launching globally in June after its Cannes Film Festival debut.", "body": "In a bold strategic pivot, Prime Video is transforming documentary filmmaking into activist media with 'Groundswell', an immersive exploration of climate solutions that pairs Hollywood star power with grassroots environmental storytelling.\n\nDirected by Josh and Rebecca Harrell Tickell, the project leverages the combined star wattage of executive producers Demi Moore and Woody Harrelson to deliver what industry insiders are calling a pragmatic 'how-to guide' for planetary rescue. The documentary arrives at a critical moment when streaming platforms increasingly view social impact content as both a moral imperative and audience magnet.\n\nPrime Video's strategic positioning signals a significant shift in streaming content philosophy. By providing a platform for solution-oriented environmental narratives, the service is positioning itself as more than just an entertainment destination \u2014 it's becoming a potential catalyst for global awareness and action.\n\nThe June premiere follows a prestigious Cannes Film Festival screening, lending immediate credibility to the project's global ambitions. Moore and Harrelson's direct involvement suggests a deeply personal commitment that transcends typical celebrity environmental endorsements.", "key_facts": ["Premiering globally on Prime Video in June", "Cannes Film Festival debut confirmed", "Co-directed by Josh and Rebecca Harrell Tickell", "Moore and Harrelson serve as executive producers", "Focused on actionable climate solutions"], "category": "premieres", "confidence_score": 9, "sources_used": ["deadline.com"], "show_title": "Groundswell", "show_ids": [], "story_hash": "108215d6fdd3a677", "published_at": "2026-05-07T23:31:53.370804+00:00", "source_url": "https://deadline.com/2026/05/groundswell-cannes-documentary-first-photos-1236887003/", "source_domain": "deadline.com", "image_url": "https://images.pexels.com/photos/34818723/pexels-photo-34818723.jpeg?auto=compress&cs=tinysrgb&dpr=2&h=650&w=940", "image_source": "pexels", "passes": true, "max_similarity": 0.277}