{"headline": "Starz Rolls Out 'Amadeus' Adaptation in High-Stakes Premium Drama Play", "lede": "The premium cabler takes a bold swing at translating the iconic film into a serialized television event, signaling continued investment in prestige historical narratives.", "body": "Starz is set to transform Peter Shaffer's celebrated theatrical meditation on musical genius into a sweeping episodic drama, challenging conventional adaptation strategies with its ambitious new series.\n\nThe network's decision to translate the Oscar-winning 1984 film into a television format represents a calculated risk in an increasingly competitive streaming landscape. Historical dramas have proven remarkably resilient, with audiences demonstrating sustained appetite for meticulously crafted period narratives that blend artistic complexity with psychological depth.\n\nWhile specific casting details remain under wraps, industry insiders suggest the production will seek performers capable of capturing the intricate psychological dynamics between Wolfgang Amadeus Mozart and Antonio Salieri. The original film's nuanced portrayal of artistic rivalry and creative jealousy set a formidable benchmark for any subsequent interpretation.\n\nStarz has been strategically positioning itself as a destination for sophisticated narrative programming, with this Mozart-centered adaptation representing another calculated expansion of its creative portfolio. The network's recent success with historically-grounded series suggests they understand the delicate alchemy required to transform celebrated cinematic properties into compelling television experiences.", "key_facts": ["Starz adapting 'Amadeus' into television series", "Follows Oscar-winning 1984 film narrative", "Historical drama continues network's prestige programming strategy", "Adaptation focuses on Mozart's complex artistic world"], "category": "premieres", "confidence_score": 7, "sources_used": ["tvline.com"], "show_title": "Amadeus", "show_ids": [], "story_hash": "1c448705354929f6", "published_at": "2026-05-08T11:32:09.277378+00:00", "source_url": "https://www.tvline.com/2163692/what-to-watch-may-8-2026-tv-shows-movies/", "source_domain": "tvline.com", "image_url": "https://image.tmdb.org/t/p/w1280/r1DUI1JmjfiuOmYvE5LnHX6atGN.jpg", "image_source": "tmdb", "passes": true, "max_similarity": 0.0511}