{"headline": "Fashion Fantasy Sequel Sashays Past Competition in International Box Office Debut", "lede": "Disney's long-anticipated 'Devil Wears Prada' sequel has stormed international theaters, delivering a knockout opening weekend that signals serious commercial potential.", "body": "## Fashion Franchise Strikes Gold Again\n\nThe return of Miranda Priestly's razor-sharp world has proven irresistible to audiences, with the film's U.K. and Ireland launch generating a robust \u00a39.3 million ($12.6 million) opening. Industry analysts are calling the performance a triumphant resurrection of the beloved fashion industry dramedy.\n\n## Global Market Dynamics\n\nUniversal's competing releases, including the music biopic 'Michael' and 'The Super Mario Galaxy Movie', found themselves trailing the fashion-forward sequel. The box office results underscore the enduring appeal of character-driven narratives with strong ensemble casts.\n\nCinematic sequels often struggle to match original magic, but this franchise appears to have defied those traditional expectations. The film's success suggests a generational nostalgia combined with fresh narrative approaches can reignite dormant entertainment properties.\n\nWhile complete international rollout details remain forthcoming, early indicators point to a potentially lucrative global run for the high-profile project.", "key_facts": ["\u00a39.3 million U.K. and Ireland opening weekend", "Disney distributed the fashion industry sequel", "Sequel demonstrates strong franchise potential", "Outperformed multiple competing releases"], "category": "premieres", "confidence_score": 9, "sources_used": ["variety.com"], "show_title": "The Devil Wears Prada 2", "show_ids": [], "story_hash": "21ae6210e13d4a9e", "published_at": "2026-05-05T16:05:40.661597+00:00", "source_url": "https://variety.com/2026/film/news/devil-wears-prada-2-uk-ireland-box-office-1236738198/", "source_domain": "variety.com", "image_url": "https://images.pexels.com/photos/7991505/pexels-photo-7991505.jpeg?auto=compress&cs=tinysrgb&dpr=2&h=650&w=940", "image_source": "pexels", "passes": true, "max_similarity": 0.2347}