{"headline": "Fox's Wild New Dating Show Puts Parents in the Matchmaking Driver's Seat", "lede": "Fox is reinventing the dating game with a provocative new reality series that hands relationship control directly to parents. Comedian Whitney Cummings will host the audacious social experiment.", "body": "Fox is doubling down on unconventional relationship programming with *Marriage Market*, a reality series that promises to upend traditional courtship by empowering parents to orchestrate their children's romantic futures.\n\nThe network's latest unscripted venture takes an unabashed dive into generational matchmaking dynamics, positioning parental intervention as the primary catalyst for romantic connection. By giving moms and dads unprecedented agency in their adult children's love lives, *Marriage Market* taps into a cultural nerve around familial expectations and romantic autonomy.\n\nCumming's sharp comedic sensibility suggests the show will balance genuine emotional stakes with sardonic commentary. Her track record of dissecting interpersonal dynamics through a comedic lens makes her an ideal guide for this potentially cringe-inducing social experiment.\n\nWhile arranged marriage concepts aren't new to television, *Marriage Market* appears positioned to deliver a distinctly American twist on the format. The series seems poised to explore generational tensions, parental expectations, and the increasingly complicated landscape of modern romance.", "key_facts": ["Whitney Cummings hosts", "Parents control matchmaking process", "Debut set for 2026", "Fox original reality series"], "category": "premieres", "confidence_score": 7, "sources_used": ["avclub.com"], "show_title": "Marriage Market", "show_ids": [], "story_hash": "b29e0ae09320baa0", "published_at": "2026-05-03T00:29:56.658571+00:00", "source_url": "https://www.avclub.com/marriage-market-fox-reality-dating-show-whitney-cummings", "source_domain": "avclub.com", "image_url": "https://images.pexels.com/photos/7991318/pexels-photo-7991318.jpeg?auto=compress&cs=tinysrgb&dpr=2&h=650&w=940", "image_source": "pexels", "passes": true, "max_similarity": 0.1561}