{"headline": "Netflix's 'Lord of the Flies' Adaptation Sparks Survival Drama Revolution", "lede": "William Golding's seminal dystopian novel gets a high-stakes streaming makeover, promising to electrify audiences with a contemporary twist on classic social breakdown.", "body": "Netflix is poised to transform William Golding's iconic exploration of human nature with its ambitious new series adaptation of *Lord of the Flies*. The streaming giant's version promises a cutting-edge reimagining of the 1954 novel, updating the narrative for a generation steeped in survival storytelling and complex character dynamics.\n\nSources close to the production reveal the series will maintain the core narrative of stranded children descending into tribal conflict, while introducing modern technological and social context. The adaptation aims to preserve the novel's profound psychological exploration while making the survival scenario feel urgent and contemporary.\n\nCasting remains under tight wraps, but industry insiders suggest the producers are seeking relatively unknown young actors who can authentically portray the visceral emotional journey of children thrust into extreme circumstances. The show's development team includes veteran television writers experienced in nuanced character-driven narratives.\n\nNetflix's track record of bold literary adaptations suggests this *Lord of the Flies* could become a landmark series, potentially redefining how classic literature translates to streaming platforms. The project represents another strategic move by the network to capture audiences hungry for intelligent, provocative storytelling.", "key_facts": ["Netflix adapting classic dystopian novel", "Modern take on Golding's original narrative", "Focus on psychological survival dynamics", "Casting emphasizes unknown young talent"], "category": "premieres", "confidence_score": 8, "sources_used": ["tvline.com"], "show_title": "Lord of the Flies", "show_ids": [], "story_hash": "bd64dbd3b0f8fcf5", "published_at": "2026-05-04T11:31:44.541142+00:00", "source_url": "https://www.tvline.com/2162058/what-to-watch-may-4-2026-tv-shows-movies/", "source_domain": "tvline.com", "image_url": "https://image.tmdb.org/t/p/w1280/yRqFvu6rIytqZlzY0pBVvZG3W0S.jpg", "image_source": "tmdb", "passes": true, "max_similarity": 0.2839}