{"headline": "Gladiator II Roars: Paul Mescal and Pedro Pascal Set to Electrify Scott's Sequel Saga", "lede": "Ridley Scott's long-awaited historical epic is charging into production with a star-studded cast that's generating serious Hollywood buzz.", "body": "Two years after first announcing the ambitious project, Ridley Scott's 'Gladiator II' is transforming from whispered speculation into a full-throttle cinematic event. The sequel to the 1999 Oscar-winning classic will feature Paul Mescal as Lucius, stepping into a narrative landscape originally defined by Russell Crowe's iconic Maximus.\n\nScott, now 86, shows no signs of slowing down. The legendary director has assembled a killer ensemble including Pedro Pascal, whose recent success in 'The Mandalorian' and 'The Last of Us' positions him as a major draw. Industry insiders suggest the film represents more than a nostalgic revisit \u2014 it's a bold reimagining of historical epic storytelling.\n\nProduction details remain tightly guarded, but early reports indicate a narrative that explores the aftermath of the original film's complex political and personal landscapes. Mescal's casting signals a generational bridge, bringing youthful energy to a franchise that defined late-90s cinema.\n\nFilm critics are already speculating about the project's potential. The combination of Scott's visionary direction, Mescal's rising star power, and the built-in audience of the original 'Gladiator' creates a perfect storm of anticipation.", "key_facts": ["Ridley Scott directing at age 86", "Paul Mescal leads the cast as Lucius", "Pedro Pascal in supporting role", "Direct sequel to 1999 Oscar-winning film", "Production currently in active development"], "category": "production", "confidence_score": 8, "sources_used": ["collider.com"], "show_title": "Gladiator II", "show_ids": [], "story_hash": "c02b963bbbb40b14", "published_at": "2026-05-02T21:09:47.570086+00:00", "source_url": "https://collider.com/ridley-scott-historical-epic-gladiator-2-streaming-success-netflix-may-2026/", "source_domain": "collider.com", "image_url": "https://images.pexels.com/photos/36287813/pexels-photo-36287813.jpeg?auto=compress&cs=tinysrgb&dpr=2&h=650&w=940", "image_source": "pexels", "passes": true, "max_similarity": 0.1636}