{"headline": "AMC's 'Dark Winds' Expands Ensemble with Rising Character Actor", "lede": "AMC's critically acclaimed Native American detective drama continues its momentum with a strategic cast addition for its upcoming fifth season. John Patrick Jordan joins the high-desert mystery series currently in production.", "body": "AMC's atmospheric crime drama *Dark Winds* is doubling down on narrative complexity with the addition of John Patrick Jordan to its ensemble cast for season 5. The series, adapted from Tony Hillerman's beloved Leaphorn & Chee book series, has consistently delivered nuanced storytelling rooted in Navajo culture and contemporary detective narratives.\n\nJordan, known for his versatile character work in projects like *The Accountant 2*, represents a strategic casting choice for the show's continued evolution. Shooting currently underway in Santa Fe, New Mexico, suggests the production remains committed to authentic location representation that has distinguished the series since its debut.\n\nThe show, which stars Zahn McClarnon as Joe Leaphorn, has garnered critical acclaim for its thoughtful portrayal of Native American law enforcement in the early 1970s. Jordan's role, while currently under wraps, promises to add another layer of narrative intrigue to the series' complex storytelling approach.\n\nWith each season, *Dark Winds* has expanded its exploration of cultural identity, criminal investigation, and the unique landscape of the Navajo Nation. Jordan's addition signals continued creative ambition for a series that has consistently pushed boundaries in television storytelling.", "key_facts": ["John Patrick Jordan joins cast for season 5", "Production currently filming in Santa Fe, New Mexico", "Based on Tony Hillerman's Leaphorn & Chee book series", "Zahn McClarnon continues to star as Joe Leaphorn"], "category": "casting", "confidence_score": 8, "sources_used": ["deadline.com"], "show_title": "Dark Winds", "show_ids": [], "story_hash": "097b4c5210924823", "published_at": "2026-05-05T21:09:07.950561+00:00", "source_url": "https://deadline.com/2026/05/john-patrick-jordan-cast-amc-dark-winds-season-5-1236881952/", "source_domain": "deadline.com", "image_url": "https://image.tmdb.org/t/p/w1280/uNvpN37f9HbvsDBQFhHU5m2EnVo.jpg", "image_source": "tmdb", "passes": true, "max_similarity": 0.3402}