{"headline": "Netflix's Aquatic Drama Dives Deep into Unexpected Friendship", "lede": "Sally Field and Lewis Pullman headline a quirky Netflix drama where an octopus becomes an unlikely emotional catalyst for human connection.", "body": "Netflix is making waves with its unconventional new drama that transforms marine life into an unexpected storytelling vehicle. The streaming giant's latest acquisition, adapted from Shelby Van Pelt's novel, represents a bold narrative experiment merging interspecies empathy with profound emotional storytelling.\n\nDirected with delicate sensitivity, the film features Alfred Molina providing voiceover narration for a remarkably intelligent octopus character who perceives the deep loneliness surrounding the aquarium's night staff. Sally Field and Lewis Pullman anchor the human drama, delivering nuanced performances that explore themes of isolation, connection, and unexpected friendship.\n\nThe project signals Netflix's continued investment in character-driven narratives that challenge traditional genre boundaries. By centering a non-human protagonist with remarkable emotional intelligence, the drama promises to deliver a uniquely touching exploration of companionship and healing.\n\nCinematographers have reportedly captured the aquarium's atmospheric spaces with remarkable subtlety, creating a visual landscape that mirrors the story's emotional depth. Early festival screenings suggest the film balances humor and pathos with remarkable dexterity.", "key_facts": ["Adapted from Shelby Van Pelt's novel", "Features Alfred Molina as octopus narrator", "Sally Field and Lewis Pullman star", "Explores themes of loneliness and connection"], "category": "premieres", "confidence_score": 8, "sources_used": ["hollywoodreporter.com"], "show_title": "Remarkably Bright Creatures", "show_ids": [], "story_hash": "4897824d736293ba", "published_at": "2026-05-07T23:32:36.163567+00:00", "source_url": "https://www.hollywoodreporter.com/movies/movie-reviews/remarkably-bright-creatures-review-1236588720/", "source_domain": "hollywoodreporter.com", "image_url": "https://images.pexels.com/photos/8422953/pexels-photo-8422953.jpeg?auto=compress&cs=tinysrgb&dpr=2&h=650&w=940", "image_source": "pexels", "passes": true, "max_similarity": 0.2721}