{"headline": "Rose Byrne's Breakout Year: Broadway and Hollywood Converge in Awards Season Triumph", "lede": "Rose Byrne has emerged as a rare triple-threat performer, securing prestigious nominations across theater and film in a single remarkable year.", "body": "Australian actor Rose Byrne has shattered industry expectations with a stunning awards season performance that spans both Broadway and Hollywood stages.\n\nByrne's electrifying portrayal of Jane in the Broadway revival of No\u00ebl Coward's *Fallen Angels* has earned her critical acclaim and a coveted Tony Award nomination. Her characterization of the 'unhinged' character demonstrates remarkable range and theatrical command.\n\nThe performer's multidisciplinary success marks a significant milestone in her career, showcasing her ability to navigate complex dramatic and comedic roles across mediums. Industry veterans note her nuanced approach to character development, which has consistently distinguished her from contemporaries.\n\nByrne's trajectory represents a sophisticated evolution from her early film work, revealing an artist capable of transcending traditional entertainment boundaries. Her Tony nomination stands alongside recent film achievements, positioning her as a formidable talent in contemporary performing arts.\n\nThe actor's strategic career choices continue to challenge traditional performer typecasting, proving her commitment to artistic integrity and creative exploration.", "key_facts": ["Tony Award nomination for 'Fallen Angels'", "Broadway and film success in same year", "No\u00ebl Coward play revival performance", "Versatile dramatic and comedic range"], "category": "premieres", "confidence_score": 9, "sources_used": ["hollywoodreporter.com"], "show_title": "Fallen Angels", "show_ids": [], "story_hash": "b1fc68c9fd517d65", "published_at": "2026-05-06T19:32:34.924363+00:00", "source_url": "https://www.hollywoodreporter.com/lifestyle/arts/rose-byrne-tony-golden-globe-oscar-nomination-one-year-1236588128/", "source_domain": "hollywoodreporter.com", "image_url": "https://image.tmdb.org/t/p/w1280/t90JcehxCwHSzuoVn25t5AXR9JA.jpg", "image_source": "tmdb", "passes": true, "max_similarity": 0.1943}