{"headline": "TV Power Duo Rob Eric and Ramy Romany Ink Major WME Deal", "lede": "Former Queer Eye creative chief Rob Eric and Bachelor in Paradise director Ramy Romany have secured agency representation that could turbocharge their nascent production company.", "body": "After launching From The Creators Productions last year, Rob Eric and Ramy Romany have quickly transformed their indie operation into an agency-backed powerhouse by signing with WME.\n\nThe partnership signals serious industry momentum for the creative team, who bring complementary skills from reality and documentary production backgrounds. Eric, previously the Chief Creative Officer at Scout Productions, arrives with significant unscripted television credibility after his transformative work on *Queer Eye*.\n\nRomany's directing experience, particularly with *Bachelor in Paradise*, provides the production company additional versatility across entertainment formats. WME's comprehensive representation promises to amplify their development and packaging capabilities across multiple genres.\n\nIndustry sources suggest the pair are positioning themselves as flexible content creators capable of producing both compelling documentary and unscripted entertainment programming. Their track record of innovative storytelling makes them an attractive prospect for streaming platforms and traditional networks seeking fresh creative voices.", "key_facts": ["Launched From The Creators Productions in 2025", "WME represents them across all media platforms", "Eric previously led creative strategy at Scout Productions", "Romany has directed major reality television series"], "category": "production", "confidence_score": 8, "sources_used": ["deadline.com"], "show_title": null, "show_ids": [], "story_hash": "e3592a4e8b11f5a5", "published_at": "2026-05-07T21:09:05.267723+00:00", "source_url": "https://deadline.com/2026/05/rob-eric-ramy-romany-wme-from-the-creators-productions-1236886652/", "source_domain": "deadline.com", "image_url": "https://images.pexels.com/photos/11043433/pexels-photo-11043433.jpeg?auto=compress&cs=tinysrgb&dpr=2&h=650&w=940", "image_source": "pexels", "passes": true, "max_similarity": 0.375}